[{"id":"1","entry":"a"},{"id":"2","entry":"able"},{"id":"3","entry":"about"},{"id":"4","entry":"above"},{"id":"5","entry":"abst"},{"id":"6","entry":"accordance"},{"id":"7","entry":"according"},{"id":"8","entry":"accordingly"},{"id":"9","entry":"across"},{"id":"10","entry":"act"},{"id":"11","entry":"actually"},{"id":"12","entry":"added"},{"id":"13","entry":"adj"},{"id":"14","entry":"affected"},{"id":"15","entry":"affecting"},{"id":"16","entry":"affects"},{"id":"17","entry":"after"},{"id":"18","entry":"afterwards"},{"id":"19","entry":"again"},{"id":"20","entry":"against"},{"id":"21","entry":"ah"},{"id":"22","entry":"all"},{"id":"23","entry":"almost"},{"id":"24","entry":"alone"},{"id":"25","entry":"along"},{"id":"26","entry":"already"},{"id":"27","entry":"also"},{"id":"28","entry":"although"},{"id":"29","entry":"always"},{"id":"30","entry":"am"},{"id":"31","entry":"among"},{"id":"32","entry":"amongst"},{"id":"33","entry":"an"},{"id":"34","entry":"and"},{"id":"35","entry":"announce"},{"id":"36","entry":"another"},{"id":"37","entry":"any"},{"id":"38","entry":"anybody"},{"id":"39","entry":"anyhow"},{"id":"40","entry":"anymore"},{"id":"41","entry":"anyone"},{"id":"42","entry":"anything"},{"id":"43","entry":"anyway"},{"id":"44","entry":"anyways"},{"id":"45","entry":"anywhere"},{"id":"46","entry":"apparently"},{"id":"47","entry":"approximately"},{"id":"48","entry":"are"},{"id":"49","entry":"aren"},{"id":"50","entry":"arent"},{"id":"51","entry":"arise"},{"id":"52","entry":"around"},{"id":"53","entry":"as"},{"id":"54","entry":"aside"},{"id":"55","entry":"ask"},{"id":"56","entry":"asking"},{"id":"57","entry":"at"},{"id":"58","entry":"auth"},{"id":"59","entry":"available"},{"id":"60","entry":"away"},{"id":"61","entry":"awfully"},{"id":"62","entry":"b"},{"id":"63","entry":"back"},{"id":"64","entry":"be"},{"id":"65","entry":"became"},{"id":"66","entry":"because"},{"id":"67","entry":"become"},{"id":"68","entry":"becomes"},{"id":"69","entry":"becoming"},{"id":"70","entry":"been"},{"id":"71","entry":"before"},{"id":"72","entry":"beforehand"},{"id":"73","entry":"begin"},{"id":"74","entry":"beginning"},{"id":"75","entry":"beginnings"},{"id":"76","entry":"begins"},{"id":"77","entry":"behind"},{"id":"78","entry":"being"},{"id":"79","entry":"believe"},{"id":"80","entry":"below"},{"id":"81","entry":"beside"},{"id":"82","entry":"besides"},{"id":"83","entry":"between"},{"id":"84","entry":"beyond"},{"id":"85","entry":"biol"},{"id":"86","entry":"both"},{"id":"87","entry":"brief"},{"id":"88","entry":"briefly"},{"id":"89","entry":"but"},{"id":"90","entry":"by"},{"id":"91","entry":"c"},{"id":"92","entry":"ca"},{"id":"93","entry":"came"},{"id":"94","entry":"can"},{"id":"95","entry":"cannot"},{"id":"96","entry":"can't"},{"id":"97","entry":"cause"},{"id":"98","entry":"causes"},{"id":"99","entry":"certain"},{"id":"100","entry":"certainly"},{"id":"101","entry":"co"},{"id":"102","entry":"com"},{"id":"103","entry":"come"},{"id":"104","entry":"comes"},{"id":"105","entry":"contain"},{"id":"106","entry":"containing"},{"id":"107","entry":"contains"},{"id":"108","entry":"could"},{"id":"109","entry":"couldnt"},{"id":"110","entry":"d"},{"id":"111","entry":"date"},{"id":"112","entry":"did"},{"id":"113","entry":"didn't"},{"id":"114","entry":"different"},{"id":"115","entry":"do"},{"id":"116","entry":"does"},{"id":"117","entry":"doesn't"},{"id":"118","entry":"doing"},{"id":"119","entry":"done"},{"id":"120","entry":"don't"},{"id":"121","entry":"down"},{"id":"122","entry":"downwards"},{"id":"123","entry":"due"},{"id":"124","entry":"during"},{"id":"125","entry":"e"},{"id":"126","entry":"each"},{"id":"127","entry":"ed"},{"id":"128","entry":"edu"},{"id":"129","entry":"effect"},{"id":"130","entry":"eg"},{"id":"131","entry":"eight"},{"id":"132","entry":"eighty"},{"id":"133","entry":"either"},{"id":"134","entry":"else"},{"id":"135","entry":"elsewhere"},{"id":"136","entry":"end"},{"id":"137","entry":"ending"},{"id":"138","entry":"enough"},{"id":"139","entry":"especially"},{"id":"140","entry":"et"},{"id":"141","entry":"et-al"},{"id":"142","entry":"etc"},{"id":"143","entry":"even"},{"id":"144","entry":"ever"},{"id":"145","entry":"every"},{"id":"146","entry":"everybody"},{"id":"147","entry":"everyone"},{"id":"148","entry":"everything"},{"id":"149","entry":"everywhere"},{"id":"150","entry":"ex"},{"id":"151","entry":"except"},{"id":"152","entry":"f"},{"id":"153","entry":"far"},{"id":"154","entry":"few"},{"id":"155","entry":"ff"},{"id":"156","entry":"fifth"},{"id":"157","entry":"first"},{"id":"158","entry":"five"},{"id":"159","entry":"fix"},{"id":"160","entry":"followed"},{"id":"161","entry":"following"},{"id":"162","entry":"follows"},{"id":"163","entry":"for"},{"id":"164","entry":"former"},{"id":"165","entry":"formerly"},{"id":"166","entry":"forth"},{"id":"167","entry":"found"},{"id":"168","entry":"four"},{"id":"169","entry":"from"},{"id":"170","entry":"further"},{"id":"171","entry":"furthermore"},{"id":"172","entry":"g"},{"id":"173","entry":"gave"},{"id":"174","entry":"get"},{"id":"175","entry":"gets"},{"id":"176","entry":"getting"},{"id":"177","entry":"give"},{"id":"178","entry":"given"},{"id":"179","entry":"gives"},{"id":"180","entry":"giving"},{"id":"181","entry":"go"},{"id":"182","entry":"goes"},{"id":"183","entry":"gone"},{"id":"184","entry":"got"},{"id":"185","entry":"gotten"},{"id":"186","entry":"h"},{"id":"187","entry":"had"},{"id":"188","entry":"happens"},{"id":"189","entry":"hardly"},{"id":"190","entry":"has"},{"id":"191","entry":"hasn't"},{"id":"192","entry":"have"},{"id":"193","entry":"haven't"},{"id":"194","entry":"having"},{"id":"195","entry":"he"},{"id":"196","entry":"hed"},{"id":"197","entry":"hence"},{"id":"198","entry":"her"},{"id":"199","entry":"here"},{"id":"200","entry":"hereafter"},{"id":"201","entry":"hereby"},{"id":"202","entry":"herein"},{"id":"203","entry":"heres"},{"id":"204","entry":"hereupon"},{"id":"205","entry":"hers"},{"id":"206","entry":"herself"},{"id":"207","entry":"hes"},{"id":"208","entry":"hi"},{"id":"209","entry":"hid"},{"id":"210","entry":"him"},{"id":"211","entry":"himself"},{"id":"212","entry":"his"},{"id":"213","entry":"hither"},{"id":"214","entry":"home"},{"id":"215","entry":"how"},{"id":"216","entry":"howbeit"},{"id":"217","entry":"however"},{"id":"218","entry":"hundred"},{"id":"219","entry":"i"},{"id":"220","entry":"id"},{"id":"221","entry":"ie"},{"id":"222","entry":"if"},{"id":"223","entry":"i'll"},{"id":"224","entry":"im"},{"id":"225","entry":"immediate"},{"id":"226","entry":"immediately"},{"id":"227","entry":"importance"},{"id":"228","entry":"important"},{"id":"229","entry":"in"},{"id":"230","entry":"inc"},{"id":"231","entry":"indeed"},{"id":"232","entry":"index"},{"id":"233","entry":"information"},{"id":"234","entry":"instead"},{"id":"235","entry":"into"},{"id":"236","entry":"invention"},{"id":"237","entry":"inward"},{"id":"238","entry":"is"},{"id":"239","entry":"isn't"},{"id":"240","entry":"it"},{"id":"241","entry":"itd"},{"id":"242","entry":"it'll"},{"id":"243","entry":"its"},{"id":"244","entry":"itself"},{"id":"245","entry":"i've"},{"id":"246","entry":"j"},{"id":"247","entry":"just"},{"id":"248","entry":"k"},{"id":"249","entry":"keep\tkeeps"},{"id":"250","entry":"kept"},{"id":"251","entry":"kg"},{"id":"252","entry":"km"},{"id":"253","entry":"know"},{"id":"254","entry":"known"},{"id":"255","entry":"knows"},{"id":"256","entry":"l"},{"id":"257","entry":"largely"},{"id":"258","entry":"last"},{"id":"259","entry":"lately"},{"id":"260","entry":"later"},{"id":"261","entry":"latter"},{"id":"262","entry":"latterly"},{"id":"263","entry":"least"},{"id":"264","entry":"less"},{"id":"265","entry":"lest"},{"id":"266","entry":"let"},{"id":"267","entry":"lets"},{"id":"268","entry":"like"},{"id":"269","entry":"liked"},{"id":"270","entry":"likely"},{"id":"271","entry":"line"},{"id":"272","entry":"little"},{"id":"273","entry":"'ll"},{"id":"274","entry":"look"},{"id":"275","entry":"looking"},{"id":"276","entry":"looks"},{"id":"277","entry":"ltd"},{"id":"278","entry":"m"},{"id":"279","entry":"made"},{"id":"280","entry":"mainly"},{"id":"281","entry":"make"},{"id":"282","entry":"makes"},{"id":"283","entry":"many"},{"id":"284","entry":"may"},{"id":"285","entry":"maybe"},{"id":"286","entry":"me"},{"id":"287","entry":"mean"},{"id":"288","entry":"means"},{"id":"289","entry":"meantime"},{"id":"290","entry":"meanwhile"},{"id":"291","entry":"merely"},{"id":"292","entry":"mg"},{"id":"293","entry":"might"},{"id":"294","entry":"million"},{"id":"295","entry":"miss"},{"id":"296","entry":"ml"},{"id":"297","entry":"more"},{"id":"298","entry":"moreover"},{"id":"299","entry":"most"},{"id":"300","entry":"mostly"},{"id":"301","entry":"mr"},{"id":"302","entry":"mrs"},{"id":"303","entry":"much"},{"id":"304","entry":"mug"},{"id":"305","entry":"must"},{"id":"306","entry":"my"},{"id":"307","entry":"myself"},{"id":"308","entry":"n"},{"id":"309","entry":"na"},{"id":"310","entry":"name"},{"id":"311","entry":"namely"},{"id":"312","entry":"nay"},{"id":"313","entry":"nd"},{"id":"314","entry":"near"},{"id":"315","entry":"nearly"},{"id":"316","entry":"necessarily"},{"id":"317","entry":"necessary"},{"id":"318","entry":"need"},{"id":"319","entry":"needs"},{"id":"320","entry":"neither"},{"id":"321","entry":"never"},{"id":"322","entry":"nevertheless"},{"id":"323","entry":"new"},{"id":"324","entry":"next"},{"id":"325","entry":"nine"},{"id":"326","entry":"ninety"},{"id":"327","entry":"no"},{"id":"328","entry":"nobody"},{"id":"329","entry":"non"},{"id":"330","entry":"none"},{"id":"331","entry":"nonetheless"},{"id":"332","entry":"noone"},{"id":"333","entry":"nor"},{"id":"334","entry":"normally"},{"id":"335","entry":"nos"},{"id":"336","entry":"not"},{"id":"337","entry":"noted"},{"id":"338","entry":"nothing"},{"id":"339","entry":"now"},{"id":"340","entry":"nowhere"},{"id":"341","entry":"o"},{"id":"342","entry":"obtain"},{"id":"343","entry":"obtained"},{"id":"344","entry":"obviously"},{"id":"345","entry":"of"},{"id":"346","entry":"off"},{"id":"347","entry":"often"},{"id":"348","entry":"oh"},{"id":"349","entry":"ok"},{"id":"350","entry":"okay"},{"id":"351","entry":"old"},{"id":"352","entry":"omitted"},{"id":"353","entry":"on"},{"id":"354","entry":"once"},{"id":"355","entry":"one"},{"id":"356","entry":"ones"},{"id":"357","entry":"only"},{"id":"358","entry":"onto"},{"id":"359","entry":"or"},{"id":"360","entry":"ord"},{"id":"361","entry":"other"},{"id":"362","entry":"others"},{"id":"363","entry":"otherwise"},{"id":"364","entry":"ought"},{"id":"365","entry":"our"},{"id":"366","entry":"ours"},{"id":"367","entry":"ourselves"},{"id":"368","entry":"out"},{"id":"369","entry":"outside"},{"id":"370","entry":"over"},{"id":"371","entry":"overall"},{"id":"372","entry":"owing"},{"id":"373","entry":"own"},{"id":"374","entry":"p"},{"id":"375","entry":"page"},{"id":"376","entry":"pages"},{"id":"377","entry":"part"},{"id":"378","entry":"particular"},{"id":"379","entry":"particularly"},{"id":"380","entry":"past"},{"id":"381","entry":"per"},{"id":"382","entry":"perhaps"},{"id":"383","entry":"placed"},{"id":"384","entry":"please"},{"id":"385","entry":"plus"},{"id":"386","entry":"poorly"},{"id":"387","entry":"possible"},{"id":"388","entry":"possibly"},{"id":"389","entry":"potentially"},{"id":"390","entry":"pp"},{"id":"391","entry":"predominantly"},{"id":"392","entry":"present"},{"id":"393","entry":"previously"},{"id":"394","entry":"primarily"},{"id":"395","entry":"probably"},{"id":"396","entry":"promptly"},{"id":"397","entry":"proud"},{"id":"398","entry":"provides"},{"id":"399","entry":"put"},{"id":"400","entry":"q"},{"id":"401","entry":"que"},{"id":"402","entry":"quickly"},{"id":"403","entry":"quite"},{"id":"404","entry":"qv"},{"id":"405","entry":"r"},{"id":"406","entry":"ran"},{"id":"407","entry":"rather"},{"id":"408","entry":"rd"},{"id":"409","entry":"re"},{"id":"410","entry":"readily"},{"id":"411","entry":"really"},{"id":"412","entry":"recent"},{"id":"413","entry":"recently"},{"id":"414","entry":"ref"},{"id":"415","entry":"refs"},{"id":"416","entry":"regarding"},{"id":"417","entry":"regardless"},{"id":"418","entry":"regards"},{"id":"419","entry":"related"},{"id":"420","entry":"relatively"},{"id":"421","entry":"research"},{"id":"422","entry":"respectively"},{"id":"423","entry":"resulted"},{"id":"424","entry":"resulting"},{"id":"425","entry":"results"},{"id":"426","entry":"right"},{"id":"427","entry":"run"},{"id":"428","entry":"s"},{"id":"429","entry":"said"},{"id":"430","entry":"same"},{"id":"431","entry":"saw"},{"id":"432","entry":"say"},{"id":"433","entry":"saying"},{"id":"434","entry":"says"},{"id":"435","entry":"sec"},{"id":"436","entry":"section"},{"id":"437","entry":"see"},{"id":"438","entry":"seeing"},{"id":"439","entry":"seem"},{"id":"440","entry":"seemed"},{"id":"441","entry":"seeming"},{"id":"442","entry":"seems"},{"id":"443","entry":"seen"},{"id":"444","entry":"self"},{"id":"445","entry":"selves"},{"id":"446","entry":"sent"},{"id":"447","entry":"seven"},{"id":"448","entry":"several"},{"id":"449","entry":"shall"},{"id":"450","entry":"she"},{"id":"451","entry":"shed"},{"id":"452","entry":"she'll"},{"id":"453","entry":"shes"},{"id":"454","entry":"should"},{"id":"455","entry":"shouldn't"},{"id":"456","entry":"show"},{"id":"457","entry":"showed"},{"id":"458","entry":"shown"},{"id":"459","entry":"showns"},{"id":"460","entry":"shows"},{"id":"461","entry":"significant"},{"id":"462","entry":"significantly"},{"id":"463","entry":"similar"},{"id":"464","entry":"similarly"},{"id":"465","entry":"since"},{"id":"466","entry":"six"},{"id":"467","entry":"slightly"},{"id":"468","entry":"so"},{"id":"469","entry":"some"},{"id":"470","entry":"somebody"},{"id":"471","entry":"somehow"},{"id":"472","entry":"someone"},{"id":"473","entry":"somethan"},{"id":"474","entry":"something"},{"id":"475","entry":"sometime"},{"id":"476","entry":"sometimes"},{"id":"477","entry":"somewhat"},{"id":"478","entry":"somewhere"},{"id":"479","entry":"soon"},{"id":"480","entry":"sorry"},{"id":"481","entry":"specifically"},{"id":"482","entry":"specified"},{"id":"483","entry":"specify"},{"id":"484","entry":"specifying"},{"id":"485","entry":"still"},{"id":"486","entry":"stop"},{"id":"487","entry":"strongly"},{"id":"488","entry":"sub"},{"id":"489","entry":"substantially"},{"id":"490","entry":"successfully"},{"id":"491","entry":"such"},{"id":"492","entry":"sufficiently"},{"id":"493","entry":"suggest"},{"id":"494","entry":"sup"},{"id":"495","entry":"sure\tt"},{"id":"496","entry":"take"},{"id":"497","entry":"taken"},{"id":"498","entry":"taking"},{"id":"499","entry":"tell"},{"id":"500","entry":"tends"},{"id":"501","entry":"th"},{"id":"502","entry":"than"},{"id":"503","entry":"thank"},{"id":"504","entry":"thanks"},{"id":"505","entry":"thanx"},{"id":"506","entry":"that"},{"id":"507","entry":"that'll"},{"id":"508","entry":"thats"},{"id":"509","entry":"that've"},{"id":"510","entry":"the"},{"id":"511","entry":"their"},{"id":"512","entry":"theirs"},{"id":"513","entry":"them"},{"id":"514","entry":"themselves"},{"id":"515","entry":"then"},{"id":"516","entry":"thence"},{"id":"517","entry":"there"},{"id":"518","entry":"thereafter"},{"id":"519","entry":"thereby"},{"id":"520","entry":"thered"},{"id":"521","entry":"therefore"},{"id":"522","entry":"therein"},{"id":"523","entry":"there'll"},{"id":"524","entry":"thereof"},{"id":"525","entry":"therere"},{"id":"526","entry":"theres"},{"id":"527","entry":"thereto"},{"id":"528","entry":"thereupon"},{"id":"529","entry":"there've"},{"id":"530","entry":"these"},{"id":"531","entry":"they"},{"id":"532","entry":"theyd"},{"id":"533","entry":"they'll"},{"id":"534","entry":"theyre"},{"id":"535","entry":"they've"},{"id":"536","entry":"think"},{"id":"537","entry":"this"},{"id":"538","entry":"those"},{"id":"539","entry":"thou"},{"id":"540","entry":"though"},{"id":"541","entry":"thoughh"},{"id":"542","entry":"thousand"},{"id":"543","entry":"throug"},{"id":"544","entry":"through"},{"id":"545","entry":"throughout"},{"id":"546","entry":"thru"},{"id":"547","entry":"thus"},{"id":"548","entry":"til"},{"id":"549","entry":"tip"},{"id":"550","entry":"to"},{"id":"551","entry":"together"},{"id":"552","entry":"too"},{"id":"553","entry":"took"},{"id":"554","entry":"toward"},{"id":"555","entry":"towards"},{"id":"556","entry":"tried"},{"id":"557","entry":"tries"},{"id":"558","entry":"truly"},{"id":"559","entry":"try"},{"id":"560","entry":"trying"},{"id":"561","entry":"ts"},{"id":"562","entry":"twice"},{"id":"563","entry":"two"},{"id":"564","entry":"u"},{"id":"565","entry":"un"},{"id":"566","entry":"under"},{"id":"567","entry":"unfortunately"},{"id":"568","entry":"unless"},{"id":"569","entry":"unlike"},{"id":"570","entry":"unlikely"},{"id":"571","entry":"until"},{"id":"572","entry":"unto"},{"id":"573","entry":"up"},{"id":"574","entry":"upon"},{"id":"575","entry":"ups"},{"id":"576","entry":"us"},{"id":"577","entry":"use"},{"id":"578","entry":"used"},{"id":"579","entry":"useful"},{"id":"580","entry":"usefully"},{"id":"581","entry":"usefulness"},{"id":"582","entry":"uses"},{"id":"583","entry":"using"},{"id":"584","entry":"usually"},{"id":"585","entry":"v"},{"id":"586","entry":"value"},{"id":"587","entry":"various"},{"id":"588","entry":"'ve"},{"id":"589","entry":"very"},{"id":"590","entry":"via"},{"id":"591","entry":"viz"},{"id":"592","entry":"vol"},{"id":"593","entry":"vols"},{"id":"594","entry":"vs"},{"id":"595","entry":"w"},{"id":"596","entry":"want"},{"id":"597","entry":"wants"},{"id":"598","entry":"was"},{"id":"599","entry":"wasnt"},{"id":"600","entry":"way"},{"id":"601","entry":"we"},{"id":"602","entry":"wed"},{"id":"603","entry":"welcome"},{"id":"604","entry":"we'll"},{"id":"605","entry":"went"},{"id":"606","entry":"were"},{"id":"607","entry":"werent"},{"id":"608","entry":"we've"},{"id":"609","entry":"what"},{"id":"610","entry":"whatever"},{"id":"611","entry":"what'll"},{"id":"612","entry":"whats"},{"id":"613","entry":"when"},{"id":"614","entry":"whence"},{"id":"615","entry":"whenever"},{"id":"616","entry":"where"},{"id":"617","entry":"whereafter"},{"id":"618","entry":"whereas"},{"id":"619","entry":"whereby"},{"id":"620","entry":"wherein"},{"id":"621","entry":"wheres"},{"id":"622","entry":"whereupon"},{"id":"623","entry":"wherever"},{"id":"624","entry":"whether"},{"id":"625","entry":"which"},{"id":"626","entry":"while"},{"id":"627","entry":"whim"},{"id":"628","entry":"whither"},{"id":"629","entry":"who"},{"id":"630","entry":"whod"},{"id":"631","entry":"whoever"},{"id":"632","entry":"whole"},{"id":"633","entry":"who'll"},{"id":"634","entry":"whom"},{"id":"635","entry":"whomever"},{"id":"636","entry":"whos"},{"id":"637","entry":"whose"},{"id":"638","entry":"why"},{"id":"639","entry":"widely"},{"id":"640","entry":"willing"},{"id":"641","entry":"wish"},{"id":"642","entry":"with"},{"id":"643","entry":"within"},{"id":"644","entry":"without"},{"id":"645","entry":"wont"},{"id":"646","entry":"words"},{"id":"647","entry":"world"},{"id":"648","entry":"would"},{"id":"649","entry":"wouldnt"},{"id":"650","entry":"www"},{"id":"651","entry":"x"},{"id":"652","entry":"y"},{"id":"653","entry":"yes"},{"id":"654","entry":"yet"},{"id":"655","entry":"you"},{"id":"656","entry":"youd"},{"id":"657","entry":"you'll"},{"id":"658","entry":"your"},{"id":"659","entry":"youre"},{"id":"660","entry":"yours"},{"id":"661","entry":"yourself"},{"id":"662","entry":"yourselves"},{"id":"663","entry":"you've"},{"id":"664","entry":"z"},{"id":"665","entry":"zero"}]